wikifaces/__init__.py
wikifaces/downloader.py
wikifaces/test.py
wikifaces/utilities.py
wikifaces-1.0.8.dist-info/LICENSE
wikifaces-1.0.8.dist-info/METADATA
wikifaces-1.0.8.dist-info/WHEEL
wikifaces-1.0.8.dist-info/top_level.txt
wikifaces-1.0.8.dist-info/RECORD
