Metadata-Version: 2.1
Name: wikifaces
Version: 1.0.8
Summary: A downloader for named images containing faces from Wiki servers.
Author-email: "Trenton W. Ford" <twford@wm.edu>, Ruiting Shao <shao72@purdue.edu>
License: MIT License
Project-URL: Homepage, https://github.com/tford9/Wiki-Faces-Downloader
Project-URL: Issues, https://github.com/tford9/Wiki-Faces-Downloader/issues
Classifier: Development Status :: 4 - Beta
Classifier: Intended Audience :: Science/Research
Classifier: License :: OSI Approved :: MIT License
Classifier: Operating System :: POSIX :: Linux
Classifier: Programming Language :: Python :: 3.8
Classifier: Programming Language :: Python :: 3.9
Requires-Python: >=3.8
License-File: LICENSE
Requires-Dist: requests
Requires-Dist: facenet-pytorch
Requires-Dist: pymediawiki
Requires-Dist: tqdm
Requires-Dist: numpy
Requires-Dist: pillow
Requires-Dist: opencv-python
Provides-Extra: dev
Requires-Dist: pylint ~=2.14.0 ; extra == 'dev'
Requires-Dist: toml ~=0.10.2 ; extra == 'dev'
Requires-Dist: yapf ~=0.32.0 ; extra == 'dev'
